setup.cfg
setup.py
events/__init__.py
events/main.py
python_events.egg-info/PKG-INFO
python_events.egg-info/SOURCES.txt
python_events.egg-info/dependency_links.txt
python_events.egg-info/top_level.txt