Metadata-Version: 1.1
Name: python-events
Version: 1.0.0
Summary: Simple event emitter library
Home-page: https://github.com/amovah/python-events
Author: Ali Movahedi
Author-email: ali_movahedi@aol.com
License: MIT
Keywords: event,emitter
Platform: UNKNOWN
Classifier: Development Status :: 4 - Beta
Classifier: Intended Audience :: Developers
Classifier: License :: OSI Approved :: MIT License
Classifier: Programming Language :: Python :: 3.5
